{
  "date": "2026-01-09",
  "track": "川崎競馬",
  "lastUpdated": "2026-01-08T11:51:30.399Z",
  "totalRaces": 12,
  "races": [
    {
      "raceNumber": "1R",
      "raceName": "３歳(六)ダ1,300m（10頭） 発走時刻12:20",
      "horseNumber": "3",
      "horseName": "エトランジュパワー",
      "reason": "",
      "confidence": "45%"
    },
    {
      "raceNumber": "2R",
      "raceName": "ランチタイムチャレンジダ1,300m（11頭） 発走時刻12:50",
      "horseNumber": "1",
      "horseName": "メジャーアピール",
      "reason": "",
      "confidence": "43%"
    },
    {
      "raceNumber": "3R",
      "raceName": "３歳(五)ダ1,400m（10頭） 発走時刻13:20",
      "horseNumber": "3",
      "horseName": "ダイバマーヤチャン",
      "reason": "",
      "confidence": "38%"
    },
    {
      "raceNumber": "3R",
      "raceName": "３歳(五)ダ1,400m（10頭） 発走時刻13:20",
      "horseNumber": "5",
      "horseName": "スピラヴィオ",
      "reason": "",
      "confidence": "39%"
    },
    {
      "raceNumber": "4R",
      "raceName": "特選 Ｃ３(二)(三)ダ1,400m（13頭） 発走時刻13:50",
      "horseNumber": "9",
      "horseName": "オリズジーニー",
      "reason": "",
      "confidence": "51%"
    },
    {
      "raceNumber": "5R",
      "raceName": "道の駅おがわまち賞ダ1,500m（12頭） 発走時刻14:20",
      "horseNumber": "9",
      "horseName": "ラフォンターナ",
      "reason": "",
      "confidence": "40%"
    },
    {
      "raceNumber": "6R",
      "raceName": "浦和８００ラウンド",
      "horseNumber": "5",
      "horseName": "クリノウィリアム",
      "reason": "",
      "confidence": "41%"
    },
    {
      "raceNumber": "6R",
      "raceName": "浦和８００ラウンド",
      "horseNumber": "8",
      "horseName": "オーシンブーケ",
      "reason": "",
      "confidence": "40%"
    },
    {
      "raceNumber": "7R",
      "raceName": "浦和８００ラウンド",
      "horseNumber": "1",
      "horseName": "ジョーサルーテ",
      "reason": "",
      "confidence": "41%"
    },
    {
      "raceNumber": "8R",
      "raceName": "お年玉（おとしだま）特別ダ1,400m（13頭） 発走時刻16:00",
      "horseNumber": "4",
      "horseName": "クーリッジテソーロ",
      "reason": "",
      "confidence": "54%"
    },
    {
      "raceNumber": "9R",
      "raceName": "初笑い（はつわらい）特別ダ2,000m（12頭） 発走時刻16:35",
      "horseNumber": "4",
      "horseName": "ハードロックスター",
      "reason": "",
      "confidence": "48%"
    },
    {
      "raceNumber": "10R",
      "raceName": "七福神（しちふくじん）特別ダ1,400m（13頭） 発走時刻17:10",
      "horseNumber": "1",
      "horseName": "ラジエル",
      "reason": "",
      "confidence": "40%"
    },
    {
      "raceNumber": "10R",
      "raceName": "七福神（しちふくじん）特別ダ1,400m（13頭） 発走時刻17:10",
      "horseNumber": "12",
      "horseName": "マシュー",
      "reason": "",
      "confidence": "49%"
    },
    {
      "raceNumber": "11R",
      "raceName": "睦月（むつき）特別ダ1,500m（10頭） 発走時刻17:45",
      "horseNumber": "1",
      "horseName": "エリンアキレウス",
      "reason": "",
      "confidence": "55%"
    },
    {
      "raceNumber": "12R",
      "raceName": "初春（はつはる）特別ダ2,000m（12頭） 発走時刻18:20",
      "horseNumber": "8",
      "horseName": "イチカノユメ",
      "reason": "",
      "confidence": "40%"
    },
    {
      "raceNumber": "12R",
      "raceName": "初春（はつはる）特別ダ2,000m（12頭） 発走時刻18:20",
      "horseNumber": "12",
      "horseName": "ツガノショウグン",
      "reason": "",
      "confidence": "42%"
    }
  ]
}
