{
  "date": "2025-12-26",
  "track": "大井競馬",
  "lastUpdated": "2025-12-25T14:08:01.480Z",
  "totalRaces": 12,
  "races": [
    {
      "raceNumber": "1R",
      "raceName": "２歳(五)(六)ダ1,400m（12頭） 発走時刻15:35",
      "horseNumber": "9",
      "horseName": "ハッピーワイド",
      "reason": "",
      "confidence": "30%"
    },
    {
      "raceNumber": "2R",
      "raceName": "２歳(五)(六)ダ1,200m（14頭） 発走時刻16:07",
      "horseNumber": "11",
      "horseName": "カナホゲラ",
      "reason": "",
      "confidence": "49%"
    },
    {
      "raceNumber": "3R",
      "raceName": "Ｃ２(十二)(十三)(十四)ダ1,600m（14頭） 発走時刻16:40",
      "horseNumber": "1",
      "horseName": "レディヴィクトリア",
      "reason": "",
      "confidence": "35%"
    },
    {
      "raceNumber": "3R",
      "raceName": "Ｃ２(十二)(十三)(十四)ダ1,600m（14頭） 発走時刻16:40",
      "horseNumber": "13",
      "horseName": "コパカバーナ",
      "reason": "",
      "confidence": "35%"
    },
    {
      "raceNumber": "4R",
      "raceName": "Ｃ２(十二)(十三)(十四)ダ1,400m（14頭） 発走時刻17:12",
      "horseNumber": "9",
      "horseName": "リッチバンケット",
      "reason": "",
      "confidence": "32%"
    },
    {
      "raceNumber": "4R",
      "raceName": "Ｃ２(十二)(十三)(十四)ダ1,400m（14頭） 発走時刻17:12",
      "horseNumber": "13",
      "horseName": "グランドターギー",
      "reason": "",
      "confidence": "36%"
    },
    {
      "raceNumber": "5R",
      "raceName": "Ｃ２(十二)(十三)(十四)ダ1,200m（14頭） 発走時刻17:45",
      "horseNumber": "14",
      "horseName": "サウンドルークス",
      "reason": "",
      "confidence": "41%"
    },
    {
      "raceNumber": "6R",
      "raceName": "コスモポリタン賞ダ2,000m（14頭） 発走時刻18:20",
      "horseNumber": "7",
      "horseName": "グラッブザトップ",
      "reason": "",
      "confidence": "41%"
    },
    {
      "raceNumber": "6R",
      "raceName": "コスモポリタン賞ダ2,000m（14頭） 発走時刻18:20",
      "horseNumber": "12",
      "horseName": "トランジェント",
      "reason": "",
      "confidence": "39%"
    },
    {
      "raceNumber": "7R",
      "raceName": "Ｂ３(五)ダ1,200m（9頭） 発走時刻18:55",
      "horseNumber": "7",
      "horseName": "リュウワンカノア",
      "reason": "",
      "confidence": "45%"
    },
    {
      "raceNumber": "8R",
      "raceName": "冬野特別ダ2,000m（16頭） 発走時刻19:30",
      "horseNumber": "9",
      "horseName": "ピンナダ",
      "reason": "",
      "confidence": "48%"
    },
    {
      "raceNumber": "9R",
      "raceName": "’２５セラフィナイト賞ダ1,800m（11頭） 発走時刻20:10",
      "horseNumber": "7",
      "horseName": "モエレサワンミヤギ",
      "reason": "",
      "confidence": "47%"
    },
    {
      "raceNumber": "10R",
      "raceName": "ラストトゥインクル２０２５賞ダ1,200m（12頭） 発走時刻20:50",
      "horseNumber": "8",
      "horseName": "ハーフブルー",
      "reason": "",
      "confidence": "40%"
    }
  ]
}
