{
  "date": "2026-02-12",
  "track": "船橋競馬",
  "lastUpdated": "2026-02-11T12:37:30.452Z",
  "totalRaces": 12,
  "races": [
    {
      "raceNumber": "1R",
      "raceName": "３歳(九)ダ1,200m（9頭） 発走時刻14:45",
      "horseNumber": "5",
      "horseName": "グランドサークル",
      "reason": "",
      "confidence": "64%"
    },
    {
      "raceNumber": "2R",
      "raceName": "３歳(八)ダ1,200m（12頭） 発走時刻15:15",
      "horseNumber": "8",
      "horseName": "ドジッコ",
      "reason": "",
      "confidence": "58%"
    },
    {
      "raceNumber": "2R",
      "raceName": "３歳(八)ダ1,200m（12頭） 発走時刻15:15",
      "horseNumber": "9",
      "horseName": "ボンシャンス",
      "reason": "",
      "confidence": "59%"
    },
    {
      "raceNumber": "3R",
      "raceName": "Ｃ２(六)(七)(八) アダ1,500m（12頭） 発走時刻15:50",
      "horseNumber": "7",
      "horseName": "ゴールドパートナー",
      "reason": "",
      "confidence": "63%"
    },
    {
      "raceNumber": "4R",
      "raceName": "Ｃ２(六)(七)(八) イダ1,200m（12頭） 発走時刻16:25",
      "horseNumber": "8",
      "horseName": "フェアリオンアイス",
      "reason": "",
      "confidence": "65%"
    },
    {
      "raceNumber": "5R",
      "raceName": "フェブラリーダッシュダ1,000m（14頭） 発走時刻16:55",
      "horseNumber": "1",
      "horseName": "チーフルガール",
      "reason": "",
      "confidence": "67%"
    },
    {
      "raceNumber": "6R",
      "raceName": "如月賞ダ1,500m（12頭） 発走時刻17:25",
      "horseNumber": "6",
      "horseName": "ズルタナイト",
      "reason": "",
      "confidence": "65%"
    },
    {
      "raceNumber": "7R",
      "raceName": "Ｃ２(六)(七)(八) ウダ1,200m（12頭） 発走時刻18:00",
      "horseNumber": "8",
      "horseName": "スプリット",
      "reason": "",
      "confidence": "69%"
    },
    {
      "raceNumber": "8R",
      "raceName": "馬い！熊本菊池水田ごぼうダ1,200m（12頭） 発走時刻18:30",
      "horseNumber": "1",
      "horseName": "レインボーポラリス",
      "reason": "",
      "confidence": "60%"
    },
    {
      "raceNumber": "9R",
      "raceName": "Ｃ１(二)(三)ダ1,600m（14頭） 発走時刻19:05",
      "horseNumber": "6",
      "horseName": "グレック",
      "reason": "",
      "confidence": "59%"
    },
    {
      "raceNumber": "10R",
      "raceName": "松戸スプリントダ1,200m（12頭） 発走時刻19:40",
      "horseNumber": "7",
      "horseName": "マイベネラブル",
      "reason": "",
      "confidence": "72%"
    },
    {
      "raceNumber": "11R",
      "raceName": "ハートビートレインダ1,600m（13頭） 発走時刻20:15",
      "horseNumber": "12",
      "horseName": "エコロネオ",
      "reason": "",
      "confidence": "63%"
    },
    {
      "raceNumber": "12R",
      "raceName": "冬夏青青特別ダ1,800m（14頭） 発走時刻20:50",
      "horseNumber": "14",
      "horseName": "ペプチドモガミ",
      "reason": "",
      "confidence": "66%"
    }
  ]
}
