{
  "date": "2026-02-02",
  "track": "川崎競馬",
  "lastUpdated": "2026-02-01T10:11:13.070Z",
  "totalRaces": 12,
  "races": [
    {
      "raceNumber": "1R",
      "raceName": "クリフハンガー賞ダ1,400m（8頭） 発走時刻15:00",
      "horseNumber": "6",
      "horseName": "トンヤイビーン",
      "reason": "",
      "confidence": "71%"
    },
    {
      "raceNumber": "2R",
      "raceName": "３歳(八)ダ1,400m（9頭） 発走時刻15:30",
      "horseNumber": "3",
      "horseName": "カナールゲイル",
      "reason": "",
      "confidence": "69%"
    },
    {
      "raceNumber": "3R",
      "raceName": "カピバラ賞",
      "horseNumber": "9",
      "horseName": "マイカグラ",
      "reason": "",
      "confidence": "56%"
    },
    {
      "raceNumber": "4R",
      "raceName": "３歳(七)ダ1,400m（9頭） 発走時刻16:30",
      "horseNumber": "4",
      "horseName": "パワーラクーン",
      "reason": "",
      "confidence": "70%"
    },
    {
      "raceNumber": "5R",
      "raceName": "迦陵頻伽（かりょうびんが）賞ダ1,500m（9頭） 発走時刻17:00",
      "horseNumber": "1",
      "horseName": "ボートレーサー",
      "reason": "",
      "confidence": "74%"
    },
    {
      "raceNumber": "6R",
      "raceName": "Ｃ２(一)ダ1,400m（13頭） 発走時刻17:30",
      "horseNumber": "3",
      "horseName": "シスターネビュラ",
      "reason": "",
      "confidence": "67%"
    },
    {
      "raceNumber": "7R",
      "raceName": "初雷（はつらい）賞",
      "horseNumber": "9",
      "horseName": "ジェンダアネモス",
      "reason": "",
      "confidence": "55%"
    },
    {
      "raceNumber": "8R",
      "raceName": "モナコ賞ダ1,500m（14頭） 発走時刻18:30",
      "horseNumber": "1",
      "horseName": "マッセダムール",
      "reason": "",
      "confidence": "60%"
    },
    {
      "raceNumber": "9R",
      "raceName": "ヴィクトリア賞ダ2,000m（12頭） 発走時刻19:05",
      "horseNumber": "1",
      "horseName": "ミヤギエンペラー",
      "reason": "",
      "confidence": "63%"
    },
    {
      "raceNumber": "10R",
      "raceName": "富士山（ふじやま）賞ダ1,600m（14頭） 発走時刻19:40",
      "horseNumber": "3",
      "horseName": "ファセット",
      "reason": "",
      "confidence": "69%"
    },
    {
      "raceNumber": "11R",
      "raceName": "活火激発（かっかげきはつ）賞",
      "horseNumber": "1",
      "horseName": "リノデスティーノ",
      "reason": "",
      "confidence": "75%"
    },
    {
      "raceNumber": "12R",
      "raceName": "大寒（だいかん）特別ダ1,400m（13頭） 発走時刻20:50",
      "horseNumber": "2",
      "horseName": "ヴィルミーキスミー",
      "reason": "",
      "confidence": "66%"
    }
  ]
}
